value_to_text
