Metadata-Version: 2.1
Name: value-to-text
Version: 1.0.2
Summary: classe para converter valor monetario para texto por extenso... e percentual por extenso
Home-page: https://github.com/edenilsonsantos/value_to_text
Author: Edenilson Fernandes dos Santos
Author-email: santoeen@gmail.com
License: MIT License
Project-URL: repository, https://github.com/edenilsonsantos/value_to_text
Keywords: value_to_text write_value numero para texto valor para texto num_to_text num2text
Classifier: Development Status :: 5 - Production/Stable
Classifier: Programming Language :: Python :: 3
Classifier: Programming Language :: Python :: 3.9
Classifier: Programming Language :: Python :: 3.10
Classifier: Programming Language :: Python :: 3.11
Classifier: License :: OSI Approved :: MIT License
Classifier: Intended Audience :: Developers
Classifier: Operating System :: POSIX :: Linux
Classifier: Operating System :: MacOS :: MacOS X
Classifier: Operating System :: Microsoft :: Windows
Classifier: Topic :: Software Development :: Libraries :: Python Modules
Requires-Python: >=3.8
License-File: LICENSE
